ouroboros/__init__.py
ouroboros/kv_cache_model.py
ouroboros/ouroboros.py
ouroboros/cache_engine/__init__.py
ouroboros/cache_engine/cache_engine.py
ouroboros/models/__init__.py
ouroboros/models/mask_making_llama.py
ouroboros/models/modeling_llama.py
ourodec-0.1.0.dist-info/LICENSE
ourodec-0.1.0.dist-info/METADATA
ourodec-0.1.0.dist-info/WHEEL
ourodec-0.1.0.dist-info/top_level.txt
ourodec-0.1.0.dist-info/RECORD
