Metadata-Version: 2.1
Name: ourodec
Version: 0.1.0
Summary: Ouroboros
Author: TsinghuaNLP
Author-email: zwl23@mails.tsinghua.edu.cn, huang-yx21@mails.tsinghua.edu.cn, hanxu2022@tsinghua.edu.cn
License-File: LICENSE
Requires-Dist: numpy >=1.21.0
Requires-Dist: tqdm
Requires-Dist: transformers >=4.36.0
Requires-Dist: datasets >=1.6.2
Requires-Dist: human-eval
Requires-Dist: lade
Requires-Dist: jinja2 >=3.1.3
